[
    {
        "title": "Apple (AAPL) Stock Quotes, Company News And Chart Analysis",
        "link": "https://www.investors.com/news/technology/apple-stock-quotes-company-news-and-chart-analysis/",
        "source": "Investor's Business Daily",
        "date": "2 days ago",
        "snippet": "Get instant access to exclusive stock lists, expert market analysis and \npowerful tools with 2 months of IBD Digital for only $20!",
        "collected_at": "2024-11-18T20:01:16.318280"
    },
    {
        "title": "How To Earn $500 A Month From Apple Stock",
        "link": "https://finance.yahoo.com/news/earn-500-month-apple-stock-150013649.html",
        "source": "Yahoo Finance",
        "date": "1 day ago",
        "snippet": "Apple Inc. (NASDAQ:AAPL) shares closed higher on Thursday despite an \noverall decline in the stock market. Consumer group Which? has filed a \u00a33 \nbillion...",
        "collected_at": "2024-11-18T20:01:16.318295"
    },
    {
        "title": "TipRanks\u2019 All-Star Analyst \u2013 Who Is the Best on AAPL Stock?",
        "link": "https://www.tipranks.com/news/tipranks-all-star-analyst-who-is-the-best-on-aapl-stock-4",
        "source": "TipRanks",
        "date": "4 days ago",
        "snippet": "The TipRanks All-star Analyst of the Day title goes to analystKrish Sankar \nof TD Cowen. Remarkably, Sankar ranks #404 out of the 9184 Wall Street \nanalysts...",
        "collected_at": "2024-11-18T20:01:16.318301"
    },
    {
        "title": "Apple Stock Investors Are Excited About Its Prospects Following New Product Releases",
        "link": "https://www.fool.com/investing/2024/11/11/apple-stock-investors-are-excited-about-its-prospe/",
        "source": "The Motley Fool",
        "date": "6 days ago",
        "snippet": "You're reading a free article with opinions that may differ from The Motley \nFool's Premium Investing Services. Become a Motley Fool member today to \nget...",
        "collected_at": "2024-11-18T20:01:16.318306"
    },
    {
        "title": "Apple, Moderna, Applied Materials fall premarket; Alibaba, Domino's Pizza rise",
        "link": "https://www.investing.com/news/stock-market-news/apple-moderna-applied-materials-fall-premarket-alibaba-dominos-pizza-rise-3725532",
        "source": "Investing.com",
        "date": "2 days ago",
        "snippet": "Investing.com -- US stock futures fell Friday, with the Wall Street indices \non course for a losing week as the post-election rally starts to fizzle out.",
        "collected_at": "2024-11-18T20:01:16.318310"
    },
    {
        "title": "Warren Buffett thinks pizza is more valuable than iPhones right now",
        "link": "https://qz.com/berkshire-hathaway-buffett-apple-dominos-pizza-stock-1851700073",
        "source": "Quartz",
        "date": "2 days ago",
        "snippet": "Buffett's Berkshire Hathaway has added 1.3 million shares of Domino's \nPizza, while shedding its stake in Apple.",
        "collected_at": "2024-11-18T20:01:16.318314"
    },
    {
        "title": "Buffett's Berkshire Buys Shares of Domino's Pizza and Pool Corp., Dumps Apple Stock",
        "link": "https://www.investopedia.com/warren-buffett-berkshire-hathaway-13f-q3-2024-apple-bank-of-america-dominos-pool-corp-8745805",
        "source": "Investopedia",
        "date": "3 days ago",
        "snippet": "Warren Buffett's Berkshire Hathaway took stakes in Domino's Pizza and \nswimming pool supplier Pool Corp. in the third quarter while continuing to \ntrim stakes...",
        "collected_at": "2024-11-18T20:01:16.318318"
    },
    {
        "title": "Is Apple Stock A Buy After Its September-Quarter Earnings Report?",
        "link": "https://www.investors.com/news/technology/apple-stock-buy-now-aapl-stock/",
        "source": "Investor's Business Daily",
        "date": "6 days ago",
        "snippet": "Apple (AAPL) stock has wavered recently on mixed sales reports for the \ncompany's iPhone 16 smartphones. Still, investors might be wondering: Is \nAAPL stock a...",
        "collected_at": "2024-11-18T20:01:16.318326"
    },
    {
        "title": "Buffett Watch: Sell Your Overvalued Apple Stock (Technical Analysis) (NASDAQ:AAPL)",
        "link": "https://seekingalpha.com/article/4737685-buffett-watch-sell-your-overvalued-apple-stock-technical-analysis",
        "source": "Seeking Alpha",
        "date": "3 days ago",
        "snippet": "Read here for an analysis of Warren Buffett's sale of Apple stock based on \ntechnical and fundamental factors, indicating a bearish outlook.",
        "collected_at": "2024-11-18T20:01:16.318332"
    },
    {
        "title": "AAPL Archives",
        "link": "https://247wallst.com/companies/aapl/",
        "source": "24/7 Wall St.",
        "date": "2 days ago",
        "snippet": "AAPL Stock Data ... Apple Inc. is a global technology leader known for its \ninnovative products and services. It offers a wide range of devices \nincluding iPhones,...",
        "collected_at": "2024-11-18T20:01:16.318336"
    },
    {
        "title": "Is There Now An Opportunity In Apple Inc. (NASDAQ:AAPL)?",
        "link": "https://finance.yahoo.com/news/now-opportunity-apple-inc-nasdaq-120016808.html?.tsrc=rss",
        "source": "Yahoo Finance",
        "date": "6 days ago",
        "snippet": "Apple Inc. ( NASDAQ:AAPL ) received a lot of attention from a substantial \nprice movement on the NASDAQGS over the last...",
        "collected_at": "2024-11-18T20:01:16.318340"
    },
    {
        "title": "George Soros\u2019 Hedge Fund Exits Position in Apple Stock",
        "link": "https://www.tipranks.com/news/george-soros-hedge-fund-exits-position-in-apple-aapl",
        "source": "TipRanks",
        "date": "41 minutes ago",
        "snippet": "George Soros' hedge fund, Soros Fund Management, recently exited its stake \nin tech giant Apple ($AAPL), resulting in a 0.49% negative impact on its \noverall...",
        "collected_at": "2024-11-18T20:01:16.318343"
    },
    {
        "title": "Billionaire Investor Warren Buffett Sold Apple Shares for a Fourth Straight Quarter. Should Investors Be Worried?",
        "link": "https://www.fool.com/investing/2024/11/14/warren-buffett-sold-apple-shares-for-a-fourth/",
        "source": "The Motley Fool",
        "date": "3 days ago",
        "snippet": "Although Buffett has been selling Apple stock, it has continued to rise in \nvalue this year.",
        "collected_at": "2024-11-18T20:01:16.318346"
    },
    {
        "title": "Apple: Decent Value Generated Despite Current Concerns, Hold (NASDAQ:AAPL)",
        "link": "https://seekingalpha.com/article/4738278-apple-stock-decent-value-generated-despite-current-concerns-hold",
        "source": "Seeking Alpha",
        "date": "6 hours ago",
        "snippet": "Economic variables like GDP growth, consumer confidence, exchange rate, and \ninterest rates influence Apple's revenue growth. Read why AAPL stock is a \nHold.",
        "collected_at": "2024-11-18T20:01:16.318350"
    },
    {
        "title": "Smart Home Devices Could Boost Apple Stock, Analyst Says",
        "link": "https://www.investors.com/news/technology/apple-stock-smart-home-devices-rumored/",
        "source": "Investor's Business Daily",
        "date": "4 days ago",
        "snippet": "Rumored smart home products in the pipeline at Apple (AAPL) could provide \nthe next leg up in the company's growth story, an Apple stock analyst \nsaid...",
        "collected_at": "2024-11-18T20:01:16.318353"
    },
    {
        "title": "Analysts Upgrade Apple Stock with Bullish Targets, Pushing Price Forecasts Higher",
        "link": "https://finance.yahoo.com/news/analysts-upgrade-apple-stock-bullish-183843316.html",
        "source": "Yahoo Finance",
        "date": "4 days ago",
        "snippet": "This week, Apple Inc. (AAPL, Financial) gained confidence from analysts, \nwho revised their recommendations and price targets for the stock, \nsuggesting that...",
        "collected_at": "2024-11-18T20:01:16.318356"
    },
    {
        "title": "Where Will Apple Stock Be in 5 Years?",
        "link": "https://www.fool.com/investing/2024/11/13/where-will-apple-stock-be-in-5-years/",
        "source": "The Motley Fool",
        "date": "4 days ago",
        "snippet": "This consumer tech powerhouse has been a market-crushing investment.",
        "collected_at": "2024-11-18T20:01:16.318360"
    },
    {
        "title": "Apple Stock (AAPL): Technical Analysis Signals a \u201cBuy\u201d",
        "link": "https://www.tipranks.com/news/apple-stock-aapl-technical-analysis-signals-a-buy",
        "source": "TipRanks",
        "date": "1 week ago",
        "snippet": "With a market cap of $2.80 trillion, tech giant Apple ($AAPL) is the second \nlargest company in the U.S. The company's diverse technology products,...",
        "collected_at": "2024-11-18T20:01:16.318366"
    },
    {
        "title": "Amazon Takes Out Google As Nvidia Snatches Apple's Crown",
        "link": "https://www.investors.com/research/magnificent-seven-stocks-latest-news-market-cap-weighting/",
        "source": "Investor's Business Daily",
        "date": "3 days ago",
        "snippet": "What are the Magnificent Seven stocks? How much market cap weighting do \nAAPL, MSFT, GOOGL, AMZN, META, TSLA and NVDA have on the Nasdaq?",
        "collected_at": "2024-11-18T20:01:16.318370"
    },
    {
        "title": "Best Stock to Buy Right Now: Amazon vs. Apple",
        "link": "https://www.fool.com/investing/2024/11/12/best-stock-to-buy-right-now-amazon-vs-apple/",
        "source": "The Motley Fool",
        "date": "6 days ago",
        "snippet": "Investors looking to add dominant tech businesses to their portfolios don't \nnecessarily have a huge list of stocks to choose from.",
        "collected_at": "2024-11-18T20:01:16.318373"
    },
    {
        "title": "Apple Inc. (NASDAQ:AAPL) Stock Holdings Lifted by Goodman Advisory Group LLC",
        "link": "https://www.marketbeat.com/instant-alerts/apple-inc-nasdaqaapl-stock-holdings-lifted-by-goodman-advisory-group-llc-2024-11-15/",
        "source": "MarketBeat",
        "date": "3 days ago",
        "snippet": "Goodman Advisory Group LLC boosted its holdings in shares of Apple Inc. \n(NASDAQ:AAPL - Free Report) by 27.0% in the 2nd quarter, according to its \nmost...",
        "collected_at": "2024-11-18T20:01:16.318377"
    },
    {
        "title": "Big News for Apple Stock Investors",
        "link": "https://www.theglobeandmail.com/investing/markets/markets-news/Motley%20Fool/29535083/big-news-for-apple-stock-investors/",
        "source": "The Globe and Mail",
        "date": "6 days ago",
        "snippet": "Apple(NASDAQ: AAPL) provided investors with critical updates you cannot \nafford to miss. *Stock prices used were the afternoon prices of Nov. 8, \n2024.",
        "collected_at": "2024-11-18T20:01:16.318380"
    },
    {
        "title": "Citi Reaffirms Apple Inc. (AAPL) as Top Pick, Maintains Buy Rating Despite China Exposure",
        "link": "https://finance.yahoo.com/news/citi-reaffirms-apple-inc-aapl-035437359.html",
        "source": "Yahoo Finance",
        "date": "5 days ago",
        "snippet": "We recently compiled a list of the 15 AI News That Should Not Be Ignored. \nIn this article, we are going to take a look at where Apple Inc. \n(NASDAQ:AAPL)...",
        "collected_at": "2024-11-18T20:01:16.318383"
    },
    {
        "title": "Apple Inc. (NASDAQ:AAPL) Stock Position Raised by Advisory Alpha LLC",
        "link": "https://www.marketbeat.com/instant-alerts/apple-inc-nasdaqaapl-shares-bought-by-advisory-alpha-llc-2024-11-17/",
        "source": "MarketBeat",
        "date": "1 day ago",
        "snippet": "Advisory Alpha LLC raised its holdings in shares of Apple Inc. (NASDAQ:AAPL \n- Free Report) by 13.4% in the 2nd quarter, according to the company in its \nmost...",
        "collected_at": "2024-11-18T20:01:16.318387"
    },
    {
        "title": "Apple Inc. (NASDAQ:AAPL) Stock Position Boosted by Savvy Advisors Inc.",
        "link": "https://www.marketbeat.com/instant-alerts/apple-inc-nasdaqaapl-stock-position-boosted-by-savvy-advisors-inc-2024-11-14/",
        "source": "MarketBeat",
        "date": "4 days ago",
        "snippet": "Savvy Advisors Inc. increased its holdings in shares of Apple Inc. \n(NASDAQ:AAPL - Free Report) by 100.3% in the second quarter, according to \nthe company in...",
        "collected_at": "2024-11-18T20:01:16.318390"
    },
    {
        "title": "AI Stocks: Tech Giants, Cloud Titans Build 2025 Momentum",
        "link": "https://www.investors.com/news/technology/artificial-intelligence-stocks/",
        "source": "Investor's Business Daily",
        "date": "2 days ago",
        "snippet": "Amid hype over artificial intelligence, the best AI stocks generate revenue \nor get a strategic edge from the fast evolving technology.",
        "collected_at": "2024-11-18T20:01:16.318393"
    },
    {
        "title": "Smart Home Devices Could Boost Apple Stock, Analyst Says",
        "link": "https://www.yahoo.com/news/m/f7ab1b51-29ed-3330-9577-f27e554859f0/smart-home-devices-could.html",
        "source": "Yahoo",
        "date": "4 days ago",
        "snippet": "Rumored smart home products at Apple could provide the next leg up in the \ncompany's growth story, an Apple stock analyst said.",
        "collected_at": "2024-11-18T20:01:16.318396"
    },
    {
        "title": "Apple stock: What does Warren Buffett know that the rest of us don\u2019t?",
        "link": "https://investorsobserver.com/news/apple-stock-what-does-warren-buffett-know-that-the-rest-of-us-dont/",
        "source": "Investorsobserver",
        "date": "4 days ago",
        "snippet": "Buffett's Berkshire Hathaway is selling AAPL and other stocks and buying \nshort-term T-bills.",
        "collected_at": "2024-11-18T20:01:16.318400"
    },
    {
        "title": "Copperwynd Financial LLC Raises Stock Holdings in Apple Inc. (NASDAQ:AAPL)",
        "link": "https://www.marketbeat.com/instant-alerts/copperwynd-financial-llc-raises-stock-holdings-in-apple-inc-nasdaqaapl-2024-11-15/",
        "source": "MarketBeat",
        "date": "3 days ago",
        "snippet": "Copperwynd Financial LLC boosted its position in Apple Inc. (NASDAQ:AAPL - \nFree Report) by 29.9% in the second quarter, according to its most recent \nForm...",
        "collected_at": "2024-11-18T20:01:16.318403"
    },
    {
        "title": "Apple (NASDAQ:AAPL) Stock Price Up 0.1% Following Analyst Upgrade",
        "link": "https://www.marketbeat.com/instant-alerts/apple-nasdaqaapl-stock-price-up-01-following-analyst-upgrade-2024-11-12/",
        "source": "MarketBeat",
        "date": "5 days ago",
        "snippet": "Apple Inc. (NASDAQ:AAPL - Get Free Report) was up 0.1% during trading on \nTuesday after UBS Group raised their price target on the stock to $236.00.",
        "collected_at": "2024-11-18T20:01:16.318406"
    },
    {
        "title": "Citi reaffirms Apple as top stock pick",
        "link": "https://macdailynews.com/2024/11/13/citi-reaffirms-apple-as-top-stock-pick/",
        "source": "MacDailyNews",
        "date": "4 days ago",
        "snippet": "Citigroup this week reaffirmed its bullish stance on Apple, maintaining a \n\"Buy\" rating and naming it as their top pick. Despite concerns\u2026",
        "collected_at": "2024-11-18T20:01:16.318409"
    },
    {
        "title": "Evercore names Apple a stock to watch in President Trump\u2019s second term",
        "link": "https://macdailynews.com/2024/11/13/evercore-names-apple-a-stock-to-watch-in-president-trumps-second-term/",
        "source": "MacDailyNews",
        "date": "4 days ago",
        "snippet": "Evercore released a post-election investor note, naming Apple as a stock to \nwatch during President-elect Donald Trump's second term\u2026",
        "collected_at": "2024-11-18T20:01:16.318413"
    },
    {
        "title": "Apple Inc. (NASDAQ:AAPL) Stock Holdings Lowered by Affinity Capital Advisors LLC",
        "link": "https://www.marketbeat.com/instant-alerts/apple-inc-nasdaqaapl-stock-holdings-lowered-by-affinity-capital-advisors-llc-2024-11-13/",
        "source": "MarketBeat",
        "date": "5 days ago",
        "snippet": "Affinity Capital Advisors LLC lowered its stake in shares of Apple Inc. \n(NASDAQ:AAPL - Free Report) by 17.9% in the second quarter, according to \nits most...",
        "collected_at": "2024-11-18T20:01:16.318416"
    },
    {
        "title": "Billionaires Are Selling Apple Stock and Picking up This TSX Stock Instead",
        "link": "https://www.fool.ca/2024/11/15/billionaires-are-selling-apple-stock-and-picking-up-this-tsx-stock-instead/",
        "source": "The Motley Fool Canada",
        "date": "2 days ago",
        "snippet": "Billionaires tend to know a bit about making money, so if they're selling \nApple stock and picking up this other stock instead, it's time to listen.",
        "collected_at": "2024-11-18T20:01:16.318419"
    },
    {
        "title": "Apple (NASDAQ:AAPL) Stock Price Expected to Rise, UBS Group Analyst Says",
        "link": "https://www.defenseworld.net/2024/11/14/apple-nasdaqaapl-stock-price-expected-to-rise-ubs-group-analyst-says.html",
        "source": "Defense World",
        "date": "4 days ago",
        "snippet": "Read Apple (NASDAQ:AAPL) Stock Price Expected to Rise, UBS Group Analyst \nSays at Defense World.",
        "collected_at": "2024-11-18T20:01:16.318423"
    },
    {
        "title": "Apple (NASDAQ:AAPL) Stock Price Up 0.1% on Analyst Upgrade",
        "link": "https://www.defenseworld.net/2024/11/13/apple-nasdaqaapl-stock-price-up-0-1-on-analyst-upgrade.html",
        "source": "Defense World",
        "date": "5 days ago",
        "snippet": "Apple Inc. (NASDAQ:AAPL \u2013 Get Free Report) traded up 0.1% during trading on \nTuesday after UBS Group raised their price target on the stock to $236.00.",
        "collected_at": "2024-11-18T20:01:16.318426"
    },
    {
        "title": "Apple Inc. (NASDAQ:AAPL) is Ascent Group LLC\u2019s Largest Position",
        "link": "https://www.defenseworld.net/2024/11/15/apple-inc-nasdaqaapl-is-ascent-group-llcs-largest-position.html",
        "source": "Defense World",
        "date": "3 days ago",
        "snippet": "Ascent Group LLC raised its position in shares of Apple Inc. (NASDAQ:AAPL \u2013 \nFree Report) by 5.2% in the second quarter, according to its most recent...",
        "collected_at": "2024-11-18T20:01:16.318429"
    },
    {
        "title": "Core Wealth Advisors Inc. Has $2.61 Million Stock Holdings in Apple Inc. (NASDAQ:AAPL)",
        "link": "https://www.defenseworld.net/2024/11/15/core-wealth-advisors-inc-has-2-61-million-stock-holdings-in-apple-inc-nasdaqaapl.html",
        "source": "Defense World",
        "date": "3 days ago",
        "snippet": "Read Core Wealth Advisors Inc. Has $2.61 Million Stock Holdings in Apple \nInc. (NASDAQ:AAPL) at Defense World.",
        "collected_at": "2024-11-18T20:01:16.318435"
    },
    {
        "title": "Apple Stock Quote | Stock Price for AAPL",
        "link": "http://business.smdailypress.com/smdailypress/quote?Symbol=NQ:AAPL",
        "source": "smdailypress.com",
        "date": "2 days ago",
        "snippet": "Apple stock quote and company news. Get the latest AAPL company stock news \n& quotes.",
        "collected_at": "2024-11-18T20:01:16.318439"
    },
    {
        "title": "Aviso Wealth Management Has $16.27 Million Stock Position in Apple Inc. (NASDAQ:AAPL)",
        "link": "https://www.defenseworld.net/2024/11/15/aviso-wealth-management-has-16-27-million-stock-position-in-apple-inc-nasdaqaapl.html",
        "source": "Defense World",
        "date": "3 days ago",
        "snippet": "Read Aviso Wealth Management Has $16.27 Million Stock Position in Apple \nInc. (NASDAQ:AAPL) at Defense World.",
        "collected_at": "2024-11-18T20:01:16.318442"
    },
    {
        "title": "Wallace Advisory Group LLC Acquires 1,855 Shares of Apple Inc. (NASDAQ:AAPL)",
        "link": "https://www.defenseworld.net/2024/11/16/wallace-advisory-group-llc-acquires-1855-shares-of-apple-inc-nasdaqaapl.html",
        "source": "Defense World",
        "date": "2 days ago",
        "snippet": "Read Wallace Advisory Group LLC Acquires 1855 Shares of Apple Inc. \n(NASDAQ:AAPL) at Defense World.",
        "collected_at": "2024-11-18T20:01:16.318446"
    },
    {
        "title": "Apple Inc. (NASDAQ:AAPL) Shares Sold by Covington Investment Advisors Inc.",
        "link": "https://www.defenseworld.net/2024/11/16/apple-inc-nasdaqaapl-shares-sold-by-covington-investment-advisors-inc.html",
        "source": "Defense World",
        "date": "1 day ago",
        "snippet": "Read Apple Inc. (NASDAQ:AAPL) Shares Sold by Covington Investment Advisors \nInc. at Defense World.",
        "collected_at": "2024-11-18T20:01:16.318449"
    },
    {
        "title": "Apple Inc. (NASDAQ:AAPL) Holdings Lessened by Nemes Rush Group LLC",
        "link": "https://www.defenseworld.net/2024/11/15/apple-inc-nasdaqaapl-holdings-lessened-by-nemes-rush-group-llc.html",
        "source": "Defense World",
        "date": "3 days ago",
        "snippet": "Read Apple Inc. (NASDAQ:AAPL) Holdings Lessened by Nemes Rush Group LLC at \nDefense World.",
        "collected_at": "2024-11-18T20:01:16.318452"
    },
    {
        "title": "Apple Inc. (NASDAQ:AAPL) Shares Sold by Core Alternative Capital",
        "link": "https://www.defenseworld.net/2024/11/16/apple-inc-nasdaqaapl-shares-sold-by-core-alternative-capital.html",
        "source": "Defense World",
        "date": "1 day ago",
        "snippet": "Read Apple Inc. (NASDAQ:AAPL) Shares Sold by Core Alternative Capital at \nDefense World.",
        "collected_at": "2024-11-18T20:01:16.318455"
    }
]